pydofus/__init__.py
pydofus/_binarystream.py
pydofus/d2p.py
pydofus/swl.py
dofus_tools_fork-0.0.2.dist-info/LICENSE
dofus_tools_fork-0.0.2.dist-info/METADATA
dofus_tools_fork-0.0.2.dist-info/WHEEL
dofus_tools_fork-0.0.2.dist-info/top_level.txt
dofus_tools_fork-0.0.2.dist-info/RECORD
