Metadata-Version: 2.1
Name: dofus-tools-fork
Version: 0.0.2
Summary: Fork of Dofus-tools by marvinroger
Home-page: https://github.com/ThibaultAr/Dofus-Tools
Author: tarloing
Author-email: thibault.arloing@hotmail.fr
License: UNKNOWN
Project-URL: Bug Tracker, https://github.com/ThibaultAr/Dofus-Tools/issues
Platform: UNKNOWN
Classifier: Programming Language :: Python :: 3
Classifier: License :: OSI Approved :: MIT License
Classifier: Operating System :: OS Independent
Requires-Python: >=3.6
License-File: LICENSE
